{"distributions":[{"id":"17746540224553y64","name":"nvbtest distro","date":"2026-03-28","ratio":1.5,"recurring":false,"frequency":"","agencies":[{"id":"17746540359599z9i","num":"agpartner","name":"asdfsadf","level":1},{"id":"17746540507981u06","num":"agpa-C001","name":"dafsdafsafsdaf","level":1},{"id":"1774654117046klxz","num":"AFPA-S002","name":"Janines Agency","level":1},{"id":"1774899521211uudu","num":"asdfsadf","name":"asdfsadf","level":1}],"pallets":[{"id":"17746540736093wkk","desc":"VeggiePuffs","type":"cases","qty":125},{"id":"1774654189730yox5","desc":"Cheese","type":"cases","qty":24},{"id":"1775174623177hxkc","desc":"Apples (Bin)","type":"cases","qty":20},{"id":"1775174628386m4ss","desc":"Bread (Trays)","type":"cases","qty":0},{"id":"1775174654520u47l","desc":"Frozen Meat","type":"cases","qty":45}],"checkedIn":["1774654117046klxz","17746540359599z9i","17746540507981u06"],"pickOrder":["17746540359599z9i","17746540507981u06","1774654117046klxz"],"palletsDone":{},"orderStatus":{"17746540359599z9i":true,"17746540507981u06":true,"1774654117046klxz":true}}],"itemLibrary":[{"name":"Apples (Bin)"},{"name":"Bread (Trays)"},{"name":"Frozen Meat"}]}